jobnotify/__init__.py
jobnotify/exceptions.py
jobnotify/jobnotify.config.sample
jobnotify/jobnotify.py
jobnotify/utils.py
jobnotify-0.1.0.dist-info/DESCRIPTION.rst
jobnotify-0.1.0.dist-info/METADATA
jobnotify-0.1.0.dist-info/RECORD
jobnotify-0.1.0.dist-info/WHEEL
jobnotify-0.1.0.dist-info/entry_points.txt
jobnotify-0.1.0.dist-info/metadata.json
jobnotify-0.1.0.dist-info/top_level.txt
