Metadata-Version: 2.0
Name: jobnotify
Version: 0.1.0
Summary: Send notifications about new job listings.
Home-page: https://github.com/matthewmckenna/jobnotify
Author: Matthew McKenna
Author-email: mattheweb.mckenna@gmail.com
License: MIT License
Requires-Dist: slackclient (>=1.0.5)
